kpca_deeponet/__init__.py
kpca_deeponet/kpca.py
kpca_deeponet/metrics.py
kpca_deeponet/nns.py
kpca_deeponet/qdeim.py
kpca_deeponet/test_cases/__init__.py
kpca_deeponet/test_cases/Cavity/__init__.py
kpca_deeponet/test_cases/Cavity/utils.py
kpca_deeponet/test_cases/NS/__init__.py
kpca_deeponet/test_cases/NS/utils.py
kpca_deeponet/test_cases/nonlinear1D/__init__.py
kpca_deeponet/test_cases/nonlinear1D/utils.py
kpca_deeponet-0.1.1.dist-info/LICENSE
kpca_deeponet-0.1.1.dist-info/METADATA
kpca_deeponet-0.1.1.dist-info/WHEEL
kpca_deeponet-0.1.1.dist-info/top_level.txt
kpca_deeponet-0.1.1.dist-info/RECORD
