Metadata-Version: 2.1
Name: kpca-deeponet
Version: 0.1.1
Summary: Nonlinear model reduction for operator learning
Home-page: https://github.com/HamidrezaEiv/KPCA-DeepONet
Author: Hamidreza Eivazi
Author-email: he76@tu-clausthal.de
Classifier: Topic :: Scientific/Engineering
Classifier: Programming Language :: Python :: 3
Classifier: License :: OSI Approved :: MIT License
Classifier: Operating System :: OS Independent
License-File: LICENSE
